fin_classifier/__init__.py
fin_classifier/classifier.py
fin_classifier/conditions.py
fin_classifier/models.py
fin_classifier-0.1.2.dist-info/METADATA
fin_classifier-0.1.2.dist-info/WHEEL
fin_classifier-0.1.2.dist-info/RECORD
