Metadata-Version: 2.4
Name: fin-classifier
Version: 0.1.2
Summary: Motor de classificação inteligente de linhas de extrato bancário com suporte a PyOdide
Project-URL: Homepage, https://github.com/tpougy/fin-classifier
Project-URL: Repository, https://github.com/tpougy/fin-classifier
Project-URL: Documentation, https://github.com/tpougy/fin-classifier#readme
Project-URL: Bug Tracker, https://github.com/tpougy/fin-classifier/issues
Author-email: Thomaz Pougy <thomazpougy@gmail.com>
Maintainer-email: Thomaz Pougy <thomazpougy@gmail.com>
License: MIT
Keywords: banking,chain-of-rule,classifier,pyodide,transactions
Classifier: Development Status :: 3 - Alpha
Classifier: Environment :: Console
Classifier: Intended Audience :: Developers
Classifier: Intended Audience :: Financial and Insurance Industry
Classifier: License :: OSI Approved :: MIT License
Classifier: Natural Language :: Portuguese (Brazilian)
Classifier: Operating System :: OS Independent
Classifier: Programming Language :: Python :: 3
Classifier: Programming Language :: Python :: 3.12
Classifier: Programming Language :: Python :: Implementation :: CPython
Classifier: Topic :: Office/Business :: Financial
Classifier: Topic :: Software Development :: Libraries :: Python Modules
Classifier: Topic :: Utilities
Requires-Python: >=3.12
Provides-Extra: dev
Requires-Dist: black>=24.0.0; extra == 'dev'
Requires-Dist: mypy>=1.10.0; extra == 'dev'
Requires-Dist: pytest-benchmark>=4.0.0; extra == 'dev'
Requires-Dist: pytest-cov>=5.0.0; extra == 'dev'
Requires-Dist: pytest-mock>=3.14.0; extra == 'dev'
Requires-Dist: pytest-xdist>=3.5.0; extra == 'dev'
Requires-Dist: pytest>=8.4.2; extra == 'dev'
Requires-Dist: ruff>=0.6.0; extra == 'dev'
Provides-Extra: pyodide
Provides-Extra: test
Requires-Dist: pytest-benchmark>=4.0.0; extra == 'test'
Requires-Dist: pytest-cov>=5.0.0; extra == 'test'
Requires-Dist: pytest-mock>=3.14.0; extra == 'test'
Requires-Dist: pytest-xdist>=3.5.0; extra == 'test'
Requires-Dist: pytest>=8.4.2; extra == 'test'
